llmfy/__init__.py
llmfy/py.typed
llmfy/exception/__init__.py
llmfy/exception/exception_handler.py
llmfy/exception/exception_mapper.py
llmfy/exception/llmfy_exception.py
llmfy/flow_engine/__init__.py
llmfy/flow_engine/flow_engine.py
llmfy/flow_engine/llmfy_pipe.py
llmfy/flow_engine/checkpointer/__init__.py
llmfy/flow_engine/checkpointer/base_checkpointer.py
llmfy/flow_engine/checkpointer/in_memory_checkpointer.py
llmfy/flow_engine/checkpointer/redis_checkpointer.py
llmfy/flow_engine/checkpointer/sql_checkpointer.py
llmfy/flow_engine/edge/__init__.py
llmfy/flow_engine/edge/edge.py
llmfy/flow_engine/helper/__init__.py
llmfy/flow_engine/helper/messages_trimmer/__init__.py
llmfy/flow_engine/helper/messages_trimmer/messages_trimmer.py
llmfy/flow_engine/helper/tools_node/__init__.py
llmfy/flow_engine/helper/tools_node/tools_node.py
llmfy/flow_engine/node/__init__.py
llmfy/flow_engine/node/node.py
llmfy/flow_engine/state/__init__.py
llmfy/flow_engine/state/memory_manager.py
llmfy/flow_engine/state/workflow_state.py
llmfy/flow_engine/stream/__init__.py
llmfy/flow_engine/stream/flow_engine_stream_response.py
llmfy/flow_engine/stream/node_stream_response.py
llmfy/flow_engine/stream/tool_node_stream_response.py
llmfy/flow_engine/visualizer/__init__.py
llmfy/flow_engine/visualizer/visualizer.py
llmfy/llmfy_core/__init__.py
llmfy/llmfy_core/llmfy.py
llmfy/llmfy_core/service_provider.py
llmfy/llmfy_core/service_type.py
llmfy/llmfy_core/embeddings/__init__.py
llmfy/llmfy_core/embeddings/base_embedding_model.py
llmfy/llmfy_core/embeddings/bedrock/__init__.py
llmfy/llmfy_core/embeddings/bedrock/bedrock_embedding.py
llmfy/llmfy_core/embeddings/openai/__init__.py
llmfy/llmfy_core/embeddings/openai/openai_embedding.py
llmfy/llmfy_core/messages/__init__.py
llmfy/llmfy_core/messages/content.py
llmfy/llmfy_core/messages/content_type.py
llmfy/llmfy_core/messages/message.py
llmfy/llmfy_core/messages/message_temp.py
llmfy/llmfy_core/messages/role.py
llmfy/llmfy_core/messages/tool_call.py
llmfy-0.4.13.dist-info/licenses/LICENSE
llmfy-0.4.13.dist-info/METADATA
llmfy-0.4.13.dist-info/WHEEL
llmfy-0.4.13.dist-info/top_level.txt
llmfy-0.4.13.dist-info/RECORD
