Metadata-Version: 2.4
Name: llmfy
Version: 0.4.13
Summary: `LLMfy` is a framework for developing applications with large language models (LLMs).
Home-page: https://github.com/irufano/llmfy
Author: irufano
Author-email: irufano.official@gmail.com
Keywords: llm,ai,llm-framework,llm-abstraction,bedrock,openai,google
Classifier: Programming Language :: Python :: 3
Classifier: License :: OSI Approved :: MIT License
Classifier: Operating System :: OS Independent
Classifier: Programming Language :: Python :: 3.11
Classifier: Programming Language :: Python :: 3.12
Classifier: Topic :: Scientific/Engineering
Classifier: Topic :: Software Development :: Libraries :: Python Modules
Requires: pydantic
Requires-Python: >=3.11
License-File: LICENSE
Requires-Dist: pydantic
Provides-Extra: openai
Requires-Dist: openai; extra == "openai"
Provides-Extra: boto3
Requires-Dist: boto3; extra == "boto3"
Provides-Extra: numpy
Requires-Dist: numpy; extra == "numpy"
Provides-Extra: faiss-cpu
Requires-Dist: faiss-cpu; extra == "faiss-cpu"
Provides-Extra: typing-extensions
Requires-Dist: typing_extensions; extra == "typing-extensions"
Provides-Extra: redis
Requires-Dist: redis; extra == "redis"
Provides-Extra: sqlalchemy
Requires-Dist: SQLAlchemy; extra == "sqlalchemy"
Dynamic: author
Dynamic: author-email
Dynamic: classifier
Dynamic: description
Dynamic: description-content-type
Dynamic: home-page
Dynamic: keywords
Dynamic: license-file
Dynamic: provides-extra
Dynamic: requires
Dynamic: requires-dist
Dynamic: requires-python
Dynamic: summary
